eazyconfig/__init__.py
eazyconfig/assets.py
eazyconfig/constants.py
eazyconfig/ezassets.py
eazyconfig/ezcfg.py
eazyconfig/unit_conversion.py
eazyconfig-2.2.dist-info/METADATA
eazyconfig-2.2.dist-info/WHEEL
eazyconfig-2.2.dist-info/top_level.txt
eazyconfig-2.2.dist-info/RECORD
