Metadata-Version: 2.1
Name: eazyconfig
Version: 2.2
Summary: Easy configuration of input files for Air Quality department
Home-page: 
Author: Saeid Alizadeh
Author-email: saeidalz96@gmail.com
Keywords: python,package,eazyconfig,AQ
Classifier: Intended Audience :: Developers
Classifier: Programming Language :: Python :: 3.11
Requires-Python: >=3.11
Requires-Dist: configparser ==6.0.0
Requires-Dist: colorama ==0.4.6
